setup.py
Products/__init__.py
Products.CCSQLMethods.egg-info/PKG-INFO
Products.CCSQLMethods.egg-info/SOURCES.txt
Products.CCSQLMethods.egg-info/dependency_links.txt
Products.CCSQLMethods.egg-info/namespace_packages.txt
Products.CCSQLMethods.egg-info/not-zip-safe
Products.CCSQLMethods.egg-info/requires.txt
Products.CCSQLMethods.egg-info/top_level.txt
Products/CCSQLMethods/LICENSE.txt
Products/CCSQLMethods/README.txt
Products/CCSQLMethods/SQL.py
Products/CCSQLMethods/VERSION.txt
Products/CCSQLMethods/__init__.py
Products/CCSQLMethods/add.dtml
Products/CCSQLMethods/edit.dtml
Products/CCSQLMethods/sqlmethod.gif
