Metadata-Version: 1.0
Name: Products.CCSQLMethods
Version: 2.0
Summary: Cache Controlled SQL Methods -- a variant of Zope's ZSQLMethods with better caching. For Zope 2.11 and above
Home-page: http://www.dieter.handshake.de/pyprojects/Zope
Author: Dieter Maurer
Author-email: dieter@handshake.de
License: BSD (see "Products/CCSQLMethods/LICENSE.txt", for details)
Keywords: Zope 2,cache,SQLMethod
Platform: UNKNOWN
Classifier: Development Status :: 5 - Production/Stable
Classifier: Intended Audience :: Developers
Classifier: License :: OSI Approved :: BSD License
Classifier: Framework :: Zope2
Classifier: Operating System :: OS Independent
Classifier: Programming Language :: Python
Classifier: Topic :: Utilities
